{
  "id": "intro",
  "title": "Purple Sector Documentation",
  "description": "Purple Sector is an AI-powered telemetry analysis platform for Assetto Corsa and Assetto Corsa Competizione. It helps sim-racing drivers improve lap times through real-time data visualization, configurable analysis panels, vehicle management, and intelligent AI coaching.",
  "source": "@site/docs/intro.md",
  "sourceDirName": ".",
  "slug": "/intro",
  "permalink": "/PurpleSector/intro",
  "draft": false,
  "unlisted": false,
  "tags": [],
  "version": "current",
  "frontMatter": {},
  "sidebar": "userGuide",
  "next": {
    "title": "Getting Started",
    "permalink": "/PurpleSector/user/getting-started"
  }
}